freedictionaryapi/__init__.py
freedictionaryapi/errors.py
freedictionaryapi/languages.py
freedictionaryapi/urls.py
freedictionaryapi/clients/__init__.py
freedictionaryapi/clients/async_client.py
freedictionaryapi/clients/base_async_client.py
freedictionaryapi/clients/base_client_interface.py
freedictionaryapi/clients/base_sync_client.py
freedictionaryapi/clients/sync_client.py
freedictionaryapi/parsers/__init__.py
freedictionaryapi/parsers/base_parser.py
freedictionaryapi/parsers/error_parser.py
freedictionaryapi/parsers/response_parser.py
freedictionaryapi/types/__init__.py
freedictionaryapi/types/base.py
freedictionaryapi/types/definition.py
freedictionaryapi/types/error.py
freedictionaryapi/types/meaning.py
freedictionaryapi/types/phonetic.py
freedictionaryapi/types/word.py
python_freeDictionaryAPI-0.9.10.dist-info/LICENSE
python_freeDictionaryAPI-0.9.10.dist-info/METADATA
python_freeDictionaryAPI-0.9.10.dist-info/WHEEL
python_freeDictionaryAPI-0.9.10.dist-info/top_level.txt
python_freeDictionaryAPI-0.9.10.dist-info/RECORD
